calculate/__init__.py
calculate/calc.py
calculate/unit_test.py
calculate_application-0.0.1.dist-info/METADATA
calculate_application-0.0.1.dist-info/WHEEL
calculate_application-0.0.1.dist-info/top_level.txt
calculate_application-0.0.1.dist-info/RECORD
